{
  "events": [
    {
      "type": "diagnostic",
      "ledger": "1",
      "ledgerClosedAt": "1970-01-01T00:00:05Z",
      "id": "0000000004294971393-0000000001",
      "pagingToken": "0000000004294971393-0000000001",
      "contractId": "0000000000000000000000000000000000000000000000000000000000000000",
      "topic": [
        "AAAADwAAAAdmbl9jYWxsAA==",
        "AAAADQAAACAAAAAAAAAAAAAAAAAAAAAAAAAAAAAAAAAAAAAAAAAAAg==",
        "AAAADwAAAAlpbmNyZW1lbnQAAAA="
      ],
      "value": {
        "xdr": "AAAAAQ=="
      }
    },
    {
      "type": "diagnostic",
      "ledger": "1",
      "ledgerClosedAt": "1970-01-01T00:00:05Z",
      "id": "0000000004294971393-0000000002",
      "pagingToken": "0000000004294971393-0000000002",
      "contractId": "0000000000000000000000000000000000000000000000000000000000000002",
      "topic": [
        "AAAADwAAAAlmbl9yZXR1cm4AAAA=",
        "AAAADwAAAAlpbmNyZW1lbnQAAAA="
      ],
      "value": {
        "xdr": "AAAAAwAAAAE="
      }
    },
    {
      "type": "diagnostic",
      "ledger": "2",
      "ledgerClosedAt": "1970-01-01T00:00:10Z",
      "id": "0000000008589938689-0000000001",
      "pagingToken": "0000000008589938689-0000000001",
      "contractId": "0000000000000000000000000000000000000000000000000000000000000000",
      "topic": [
        "AAAADwAAAAdmbl9jYWxsAA==",
        "AAAADQAAACAAAAAAAAAAAAAAAAAAAAAAAAAAAAAAAAAAAAAAAAAAAg==",
        "AAAADwAAAAlpbmNyZW1lbnQAAAA="
      ],
      "value": {
        "xdr": "AAAAAQ=="
      }
    },
    {
      "type": "diagnostic",
      "ledger": "2",
      "ledgerClosedAt": "1970-01-01T00:00:10Z",
      "id": "0000000008589938689-0000000002",
      "pagingToken": "0000000008589938689-0000000002",
      "contractId": "0000000000000000000000000000000000000000000000000000000000000002",
      "topic": [
        "AAAADwAAAAlmbl9yZXR1cm4AAAA=",
        "AAAADwAAAAlpbmNyZW1lbnQAAAA="
      ],
      "value": {
        "xdr": "AAAAAwAAAAE="
      }
    },
    {
      "type": "diagnostic",
      "ledger": "3",
      "ledgerClosedAt": "1970-01-01T00:00:15Z",
      "id": "0000000012884905985-0000000001",
      "pagingToken": "0000000012884905985-0000000001",
      "contractId": "0000000000000000000000000000000000000000000000000000000000000000",
      "topic": [
        "AAAADwAAAAdmbl9jYWxsAA==",
        "AAAADQAAACAAAAAAAAAAAAAAAAAAAAAAAAAAAAAAAAAAAAAAAAAAAg==",
        "AAAADwAAAAlpbmNyZW1lbnQAAAA="
      ],
      "value": {
        "xdr": "AAAAAQ=="
      }
    },
    {
      "type": "diagnostic",
      "ledger": "3",
      "ledgerClosedAt": "1970-01-01T00:00:15Z",
      "id": "0000000012884905985-0000000002",
      "pagingToken": "0000000012884905985-0000000002",
      "contractId": "0000000000000000000000000000000000000000000000000000000000000002",
      "topic": [
        "AAAADwAAAAlmbl9yZXR1cm4AAAA=",
        "AAAADwAAAAlpbmNyZW1lbnQAAAA="
      ],
      "value": {
        "xdr": "AAAAAwAAAAE="
      }
    },
    {
      "type": "diagnostic",
      "ledger": "4",
      "ledgerClosedAt": "1970-01-01T00:00:20Z",
      "id": "0000000017179873281-0000000001",
      "pagingToken": "0000000017179873281-0000000001",
      "contractId": "0000000000000000000000000000000000000000000000000000000000000000",
      "topic": [
        "AAAADwAAAAdmbl9jYWxsAA==",
        "AAAADQAAACAAAAAAAAAAAAAAAAAAAAAAAAAAAAAAAAAAAAAAAAAAAg==",
        "AAAADwAAAAlpbmNyZW1lbnQAAAA="
      ],
      "value": {
        "xdr": "AAAAAQ=="
      }
    },
    {
      "type": "diagnostic",
      "ledger": "4",
      "ledgerClosedAt": "1970-01-01T00:00:20Z",
      "id": "0000000017179873281-0000000002",
      "pagingToken": "0000000017179873281-0000000002",
      "contractId": "0000000000000000000000000000000000000000000000000000000000000002",
      "topic": [
        "AAAADwAAAAlmbl9yZXR1cm4AAAA=",
        "AAAADwAAAAlpbmNyZW1lbnQAAAA="
      ],
      "value": {
        "xdr": "AAAAAwAAAAE="
      }
    },
    {
      "type": "diagnostic",
      "ledger": "5",
      "ledgerClosedAt": "1970-01-01T00:00:25Z",
      "id": "0000000021474840577-0000000001",
      "pagingToken": "0000000021474840577-0000000001",
      "contractId": "0000000000000000000000000000000000000000000000000000000000000000",
      "topic": [
        "AAAADwAAAAdmbl9jYWxsAA==",
        "AAAADQAAACAAAAAAAAAAAAAAAAAAAAAAAAAAAAAAAAAAAAAAAAAAAQ==",
        "AAAADwAAAAlpbmNyZW1lbnQAAAA="
      ],
      "value": {
        "xdr": "AAAAAQ=="
      }
    },
    {
      "type": "diagnostic",
      "ledger": "5",
      "ledgerClosedAt": "1970-01-01T00:00:25Z",
      "id": "0000000021474840577-0000000002",
      "pagingToken": "0000000021474840577-0000000002",
      "contractId": "0000000000000000000000000000000000000000000000000000000000000001",
      "topic": [
        "AAAADwAAAAlmbl9yZXR1cm4AAAA=",
        "AAAADwAAAAlpbmNyZW1lbnQAAAA="
      ],
      "value": {
        "xdr": "AAAAAwAAAAE="
      }
    },
    {
      "type": "diagnostic",
      "ledger": "6",
      "ledgerClosedAt": "1970-01-01T00:00:30Z",
      "id": "0000000025769807873-0000000001",
      "pagingToken": "0000000025769807873-0000000001",
      "contractId": "0000000000000000000000000000000000000000000000000000000000000000",
      "topic": [
        "AAAADwAAAAdmbl9jYWxsAA==",
        "AAAADQAAACAAAAAAAAAAAAAAAAAAAAAAAAAAAAAAAAAAAAAAAAAAAQ==",
        "AAAADwAAAAlpbmNyZW1lbnQAAAA="
      ],
      "value": {
        "xdr": "AAAAAQ=="
      }
    },
    {
      "type": "diagnostic",
      "ledger": "6",
      "ledgerClosedAt": "1970-01-01T00:00:30Z",
      "id": "0000000025769807873-0000000002",
      "pagingToken": "0000000025769807873-0000000002",
      "contractId": "0000000000000000000000000000000000000000000000000000000000000001",
      "topic": [
        "AAAADwAAAAlmbl9yZXR1cm4AAAA=",
        "AAAADwAAAAlpbmNyZW1lbnQAAAA="
      ],
      "value": {
        "xdr": "AAAAAwAAAAE="
      }
    },
    {
      "type": "diagnostic",
      "ledger": "7",
      "ledgerClosedAt": "1970-01-01T00:00:35Z",
      "id": "0000000030064775169-0000000001",
      "pagingToken": "0000000030064775169-0000000001",
      "contractId": "0000000000000000000000000000000000000000000000000000000000000000",
      "topic": [
        "AAAADwAAAAdmbl9jYWxsAA==",
        "AAAADQAAACAAAAAAAAAAAAAAAAAAAAAAAAAAAAAAAAAAAAAAAAAAAQ==",
        "AAAADwAAAAlpbmNyZW1lbnQAAAA="
      ],
      "value": {
        "xdr": "AAAAAQ=="
      }
    },
    {
      "type": "diagnostic",
      "ledger": "7",
      "ledgerClosedAt": "1970-01-01T00:00:35Z",
      "id": "0000000030064775169-0000000002",
      "pagingToken": "0000000030064775169-0000000002",
      "contractId": "0000000000000000000000000000000000000000000000000000000000000001",
      "topic": [
        "AAAADwAAAAlmbl9yZXR1cm4AAAA=",
        "AAAADwAAAAlpbmNyZW1lbnQAAAA="
      ],
      "value": {
        "xdr": "AAAAAwAAAAE="
      }
    },
    {
      "type": "diagnostic",
      "ledger": "8",
      "ledgerClosedAt": "1970-01-01T00:00:40Z",
      "id": "0000000034359742465-0000000001",
      "pagingToken": "0000000034359742465-0000000001",
      "contractId": "0000000000000000000000000000000000000000000000000000000000000000",
      "topic": [
        "AAAADwAAAAdmbl9jYWxsAA==",
        "AAAADQAAACAAAAAAAAAAAAAAAAAAAAAAAAAAAAAAAAAAAAAAAAAAAQ==",
        "AAAADwAAAAlpbmNyZW1lbnQAAAA="
      ],
      "value": {
        "xdr": "AAAAAQ=="
      }
    },
    {
      "type": "diagnostic",
      "ledger": "8",
      "ledgerClosedAt": "1970-01-01T00:00:40Z",
      "id": "0000000034359742465-0000000002",
      "pagingToken": "0000000034359742465-0000000002",
      "contractId": "0000000000000000000000000000000000000000000000000000000000000001",
      "topic": [
        "AAAADwAAAAlmbl9yZXR1cm4AAAA=",
        "AAAADwAAAAlpbmNyZW1lbnQAAAA="
      ],
      "value": {
        "xdr": "AAAAAwAAAAE="
      }
    },
    {
      "type": "diagnostic",
      "ledger": "9",
      "ledgerClosedAt": "1970-01-01T00:00:45Z",
      "id": "0000000038654709761-0000000001",
      "pagingToken": "0000000038654709761-0000000001",
      "contractId": "0000000000000000000000000000000000000000000000000000000000000000",
      "topic": [
        "AAAADwAAAAdmbl9jYWxsAA==",
        "AAAADQAAACAAAAAAAAAAAAAAAAAAAAAAAAAAAAAAAAAAAAAAAAAAAQ==",
        "AAAADwAAAAlpbmNyZW1lbnQAAAA="
      ],
      "value": {
        "xdr": "AAAAAQ=="
      }
    },
    {
      "type": "diagnostic",
      "ledger": "9",
      "ledgerClosedAt": "1970-01-01T00:00:45Z",
      "id": "0000000038654709761-0000000002",
      "pagingToken": "0000000038654709761-0000000002",
      "contractId": "0000000000000000000000000000000000000000000000000000000000000001",
      "topic": [
        "AAAADwAAAAlmbl9yZXR1cm4AAAA=",
        "AAAADwAAAAlpbmNyZW1lbnQAAAA="
      ],
      "value": {
        "xdr": "AAAAAwAAAAE="
      }
    }
  ],
  "latestLedger": 9
}